colt/__init__.py
colt/answers.py
colt/ask.py
colt/colt.py
colt/commandline.py
colt/config.py
colt/configast.py
colt/generator.py
colt/lazyimport.py
colt/obj.py
colt/parser.py
colt/parser_settings_generator.py
colt/pluginloader.py
colt/plugins.py
colt/presets.py
colt/qform.py
colt/questions.py
colt/slottedcls.py
colt/sphinx.py
colt/validator.py
colt/webform.py
colt/tools/__init__.py
colt/tools/actions.py
colt/workflow/__init__.py
colt/workflow/_types.py
colt/workflow/actions.py
colt/workflow/language.py
colt/workflow/workflow.py
pycolt-0.6.0.dist-info/AUTHORS.rst
pycolt-0.6.0.dist-info/LICENSE
pycolt-0.6.0.dist-info/METADATA
pycolt-0.6.0.dist-info/WHEEL
pycolt-0.6.0.dist-info/top_level.txt
pycolt-0.6.0.dist-info/RECORD
