Metadata-Version: 2.1
Name: pycolt
Version: 0.6.0
Summary: Command Line Tool for Python
Home-page: https://github.com/mfsjmenger/colt
Author: Maximilian F.S.J. Menger
Author-email: m.f.s.j.menger@rug.nl
License: Apache License v2.0
Keywords: pycolt
Platform: UNKNOWN
Classifier: Development Status :: 2 - Pre-Alpha
Classifier: Intended Audience :: Developers
Classifier: License :: OSI Approved :: Apache Software License
Classifier: Natural Language :: English
Classifier: Programming Language :: Python :: 3.6
Classifier: Programming Language :: Python :: 3.7
Classifier: Programming Language :: Python :: 3.8
Requires-Python: >=3.6
License-File: LICENSE
License-File: AUTHORS.rst
